bluetree_shopify_book/__init__.py
bluetree_shopify_book/adapters.py
bluetree_shopify_book/app.py
bluetree_shopify_book/csv.py
bluetree_shopify_book/document.graphql
bluetree_shopify_book/exceptions.py
bluetree_shopify_book/schema.py
bluetree_shopify_book/utils.py
bluetree_shopify_book/validators.py
bluetree_shopify_book-0.2.3.dist-info/LICENSE.txt
bluetree_shopify_book-0.2.3.dist-info/METADATA
bluetree_shopify_book-0.2.3.dist-info/WHEEL
bluetree_shopify_book-0.2.3.dist-info/top_level.txt
bluetree_shopify_book-0.2.3.dist-info/RECORD
