Metadata-Version: 2.1
Name: bluetree-shopify-book
Version: 0.2.3
Summary: A Python package for managing books in Shopify
Home-page: https://github.com/sikegame/bluetree-shopify-book
Author: Shinsuke JJ Ikegame
Author-email: jj@digitalnomad.jp
Project-URL: Bug Tracker, https://github.com/sikegame/bluetree-shopify-book/issues
Project-URL: repository, https://github.com/sikegame/bluetree-shopify-book
Classifier: Programming Language :: Python :: 3
Classifier: License :: OSI Approved :: MIT License
Classifier: Operating System :: OS Independent
Requires-Python: >=3.9
License-File: LICENSE.txt
Requires-Dist: aiolimiter (==1.0.0)
Requires-Dist: attrs (==22.2.0)
Requires-Dist: click (==8.1.3)
Requires-Dist: exceptiongroup (==1.1.0)
Requires-Dist: iniconfig (==2.0.0)
Requires-Dist: mypy-extensions (==1.0.0)
Requires-Dist: packaging (==23.0)
Requires-Dist: pathspec (==0.11.0)
Requires-Dist: platformdirs (==3.0.0)
Requires-Dist: pluggy (==1.0.0)
Requires-Dist: pyactiveresource (==2.2.2)
Requires-Dist: pydantic (==1.10.5)
Requires-Dist: PyJWT (==2.6.0)
Requires-Dist: PyYAML (==6.0)
Requires-Dist: ShopifyAPI (==12.2.0)
Requires-Dist: six (==1.16.0)
Requires-Dist: tomli (==2.0.1)
Requires-Dist: typing-extensions (==4.5.0)
